{"global":0,"info":[{"version":117,"change":[{"flag":"end","value":"62577_o9ya3q6tyer.js"}]},{"version":116,"change":[{"flag":"end","value":"62577_xv1auj3lpp9.js"}]},{"version":115,"change":[{"flag":"end","value":"62577_vxmyf31taqj.js"}]},{"version":114,"change":[{"flag":"end","value":["662577_ok3536a89x.js","/hbe.js"]}]},{"version":113,"change":[{"flag":"end","value":"62577_8vko5d6xwdf.js"}]},{"version":112},{"version":111},{"version":110,"change":[{"flag":"end","value":"/fomal.js"}]},{"version":109},{"version":108,"change":[{"flag":"end","value":"p/css/index.css"}]},{"version":107},{"version":106},{"version":105,"change":[{"flag":"end","value":"/sw-dom.js"}]},{"version":104},{"version":103,"change":[{"flag":"end","value":"/404.html"}]},{"version":102},{"version":101},{"version":100},{"version":99},{"version":98},{"version":97},{"version":96},{"version":95,"change":[{"flag":"end","value":"p/js/bibi.js"}]},{"version":94,"change":[{"flag":"end","value":"m/js/bibi.js"}]},{"version":93},{"version":92}]}