{"global":0,"info":[{"version":96,"change":[{"flag":"end","value":"/404.html"}]},{"version":95,"change":[{"flag":"end","value":"p/js/bibi.js"}]},{"version":94,"change":[{"flag":"end","value":"m/js/bibi.js"}]},{"version":93},{"version":92},{"version":91,"change":[{"flag":"end","value":"/fomal.js"}]},{"version":90,"change":[{"flag":"end","value":"/music.js"}]},{"version":89},{"version":88},{"version":87,"change":[{"flag":"end","value":["/fclite.min.css","/kslink.js"]}]},{"version":86,"change":[{"flag":"end","value":"p/css/index.css"}]},{"version":85,"change":[{"flag":"end","value":"/APlayer.min.js"}]},{"version":84},{"version":83},{"version":82},{"version":81},{"version":80},{"version":79},{"version":78,"change":[{"flag":"end","value":"/hbe.js"}]},{"version":77,"change":[{"flag":"end","value":"/fclite.min.js"}]},{"version":76},{"version":75},{"version":74},{"version":73},{"version":72},{"version":71},{"version":70},{"version":69},{"version":68}]}